Metadata-Version: 1.1
Name: django-qr-creator
Version: 0.1.4
Summary: A simple Django app to create QR images in template
Home-page: https://github.com/alexperezortuno/django-qr-creator
Author: Alexander Perez Ortuño
Author-email: alexperezortuno@gmail.com
License: BSD License
Platform: UNKNOWN
Classifier: Environment :: Web Environment
Classifier: Framework :: Django
Classifier: Framework :: Django :: 2.0
Classifier: Intended Audience :: Developers
Classifier: License :: OSI Approved :: BSD License
Classifier: Operating System :: OS Independent
Classifier: Programming Language :: Python
Classifier: Programming Language :: Python :: 3.5
Classifier: Programming Language :: Python :: 3.6
Classifier: Topic :: Internet :: WWW/HTTP
Classifier: Topic :: Internet :: WWW/HTTP :: Dynamic Content
